contact_form_smtp/__init__.py
contact_form_smtp/app.py
contact_form_smtp/cli.py
contact_form_smtp/settings.py
contact_form_smtp/version.py
contact_form_smtp-1.0.1.dist-info/entry_points.txt
contact_form_smtp-1.0.1.dist-info/LICENSE
contact_form_smtp-1.0.1.dist-info/WHEEL
contact_form_smtp-1.0.1.dist-info/METADATA
contact_form_smtp-1.0.1.dist-info/RECORD
